pybite/__init__.py
pybite/iterate.py
pybite/file/__init__.py
pybite/file/_open.py
pybite/file/chunk.py
pybite/file/iterate.py
pybite-1.4.2.dist-info/LICENSE
pybite-1.4.2.dist-info/METADATA
pybite-1.4.2.dist-info/WHEEL
pybite-1.4.2.dist-info/top_level.txt
pybite-1.4.2.dist-info/RECORD
