Metadata-Version: 2.1
Name: pybite
Version: 1.4.2
Summary: Chunk by chunk iteration made easier
Home-page: https://github.com/metadeta96/pybite
Author: metadeta96
Author-email: metadeta96@gmail.com
License: UNKNOWN
Download-URL: https://github.com/metadeta96/pybite
Keywords: iteration,iter,iterable,sequence,list,tuple,dict,array,chunk,block,processing,data,split,slice,file,buffer
Platform: UNKNOWN
Classifier: Programming Language :: Python :: 3
Classifier: License :: OSI Approved :: GNU Lesser General Public License v3 or later (LGPLv3+)
Classifier: Operating System :: OS Independent
Requires-Python: >=3.5
